openmlcrawler/__init__.py
openmlcrawler/cli.py
openmlcrawler/config/pipeline_example.yaml
openmlcrawler-1.0.0.dist-info/licenses/LICENSE
openmlcrawler-1.0.0.dist-info/METADATA
openmlcrawler-1.0.0.dist-info/WHEEL
openmlcrawler-1.0.0.dist-info/entry_points.txt
openmlcrawler-1.0.0.dist-info/top_level.txt
openmlcrawler-1.0.0.dist-info/RECORD
