Metadata-Version: 2.4
Name: openmlcrawler
Version: 1.0.0
Summary: A unified framework for crawling and preparing ML-ready datasets
Home-page: https://github.com/krish567366/openmlcrawler
Author: Krishna Bajpai, Vedanshi Gupta
Author-email: Krishna Bajpai <krishna@krishnabajpai.me>, Vedanshi Gupta <krishna@krishnabajpai.me>
License: MIT
Project-URL: Homepage, https://github.com/krish567366/openmlcrawler
Project-URL: Documentation, https://krish567366.github.io/openmlcrawler/
Project-URL: Repository, https://github.com/krish567366/openmlcrawler
Project-URL: Issues, https://github.com/krish567366/openmlcrawler/issues
Classifier: Development Status :: 3 - Alpha
Classifier: Intended Audience :: Developers
Classifier: Intended Audience :: Science/Research
Classifier: License :: OSI Approved :: MIT License
Classifier: Operating System :: OS Independent
Classifier: Programming Language :: Python :: 3
Classifier: Programming Language :: Python :: 3.8
Classifier: Programming Language :: Python :: 3.9
Classifier: Programming Language :: Python :: 3.10
Classifier: Programming Language :: Python :: 3.11
Classifier: Topic :: Scientific/Engineering :: Artificial Intelligence
Classifier: Topic :: Internet :: WWW/HTTP
Classifier: Topic :: Software Development :: Libraries :: Python Modules
Requires-Python: >=3.8
License-File: LICENSE
Requires-Dist: pandas>=1.3.0
Requires-Dist: requests>=2.25.0
Requires-Dist: numpy>=1.20.0
Requires-Dist: scikit-learn>=1.0.0
Requires-Dist: beautifulsoup4>=4.9.0
Requires-Dist: lxml>=4.6.0
Requires-Dist: pyarrow>=6.0.0
Requires-Dist: nltk>=3.6.0
Requires-Dist: pdfplumber>=0.6.0
Requires-Dist: aiohttp>=3.8.0
Requires-Dist: playwright>=1.20.0
Requires-Dist: typer>=0.4.0
Requires-Dist: rich>=10.0.0
Provides-Extra: dev
Requires-Dist: pytest>=6.0.0; extra == "dev"
Requires-Dist: pytest-cov>=2.0.0; extra == "dev"
Requires-Dist: black>=21.0.0; extra == "dev"
Requires-Dist: flake8>=3.9.0; extra == "dev"
Requires-Dist: mypy>=0.900; extra == "dev"
Requires-Dist: sphinx>=4.0.0; extra == "dev"
Requires-Dist: sphinx-rtd-theme>=1.0.0; extra == "dev"
Provides-Extra: nlp
Requires-Dist: transformers>=4.0.0; extra == "nlp"
Requires-Dist: torch>=1.9.0; extra == "nlp"
Requires-Dist: datasets>=1.0.0; extra == "nlp"
Provides-Extra: async
Requires-Dist: aiofiles>=0.7.0; extra == "async"
Requires-Dist: asyncio-throttle>=1.0.0; extra == "async"
Dynamic: author
Dynamic: home-page
Dynamic: license-file
Dynamic: requires-python
